openmc_source_plotter/__init__.py
openmc_source_plotter/_version.py
openmc_source_plotter/core.py
openmc_source_plotter/material.py
openmc_source_plotter-0.7.1.dist-info/LICENSE.txt
openmc_source_plotter-0.7.1.dist-info/METADATA
openmc_source_plotter-0.7.1.dist-info/WHEEL
openmc_source_plotter-0.7.1.dist-info/entry_points.txt
openmc_source_plotter-0.7.1.dist-info/top_level.txt
openmc_source_plotter-0.7.1.dist-info/RECORD
