Metadata-Version: 2.1
Name: openmc_source_plotter
Version: 0.7.1
Summary: A Python package for extracting and plotting the locations, directions, energy distributions of OpenMC source particles.
Author-email: Jonathan Shimwell <mail@jshimwell.com>
License: MIT License
Project-URL: Homepage, https://github.com/fusion-energy/openmc_source_plotter
Project-URL: Bug Tracker, https://github.com/fusion-energy/openmc_source_plotter/issues
Keywords: energy,plot,source,particle,coordinates,direction,openmc,gamma
Classifier: Programming Language :: Python :: 3
Classifier: License :: OSI Approved :: MIT License
Classifier: Operating System :: OS Independent
Requires-Python: >=3.8
License-File: LICENSE.txt
Requires-Dist: h5py
Requires-Dist: plotly
Requires-Dist: numpy
Provides-Extra: gammas
Requires-Dist: lineid-plot ; extra == 'gammas'
Provides-Extra: tests
Requires-Dist: pytest ; extra == 'tests'
